opx_plus.py
opx_plus-0.1.8.dist-info/METADATA
opx_plus-0.1.8.dist-info/WHEEL
opx_plus-0.1.8.dist-info/licenses/LICENSE.txt
opx_plus-0.1.8.dist-info/RECORD
