Metadata-Version: 2.1
Name: opx_plus
Version: 0.1.8
Summary: Adds additional functionality on top of OpenPyXL
Project-URL: Homepage, https://github.com/StevenWilson9/OPX_Plus
Project-URL: Bug Tracker, https://github.com/StevenWilson9/OPX_Plus/issues
Author: Steven Wilson
License-File: LICENSE.txt
Classifier: License :: OSI Approved :: MIT License
Classifier: Operating System :: OS Independent
Classifier: Programming Language :: Python :: 3
Requires-Python: >=3.8
Requires-Dist: openpyxl~=3.0.9
